cs/testutils.py
cs_testutils-20251020.dist-info/WHEEL
cs_testutils-20251020.dist-info/METADATA
cs_testutils-20251020.dist-info/RECORD
